asphalt/redis/__init__.py
asphalt/redis/component.py
asphalt/redis/py.typed
asphalt_redis-4.1.0.dist-info/LICENSE
asphalt_redis-4.1.0.dist-info/METADATA
asphalt_redis-4.1.0.dist-info/WHEEL
asphalt_redis-4.1.0.dist-info/entry_points.txt
asphalt_redis-4.1.0.dist-info/top_level.txt
asphalt_redis-4.1.0.dist-info/RECORD
