Metadata-Version: 2.1
Name: asphalt-redis
Version: 4.1.0
Summary: Redis integration component for the Asphalt framework
Author-email: Alex Grönholm <alex.gronholm@nextday.fi>
License: Apache License 2.0
Project-URL: Homepage, https://github.com/asphalt-framework/asphalt-redis
Classifier: Development Status :: 5 - Production/Stable
Classifier: Intended Audience :: Developers
Classifier: License :: OSI Approved :: Apache Software License
Classifier: Topic :: Database
Classifier: Typing :: Typed
Classifier: Programming Language :: Python
Classifier: Programming Language :: Python :: 3.7
Classifier: Programming Language :: Python :: 3.8
Classifier: Programming Language :: Python :: 3.9
Classifier: Programming Language :: Python :: 3.10
Classifier: Programming Language :: Python :: 3.11
Classifier: Programming Language :: Python :: 3.12
Requires-Python: >=3.7
License-File: LICENSE
Requires-Dist: asphalt (~=4.7)
Requires-Dist: redis (>=4.2.0)
Provides-Extra: doc
Requires-Dist: Sphinx (>=6.0) ; extra == 'doc'
Requires-Dist: sphinx-rtd-theme (>=1.2.0) ; extra == 'doc'
Requires-Dist: sphinx-autodoc-typehints (>=1.22) ; extra == 'doc'
Provides-Extra: test
Requires-Dist: pytest ; extra == 'test'
Requires-Dist: pytest-cov ; extra == 'test'
Requires-Dist: pytest-asyncio ; extra == 'test'
